tests/test_annotators.py
vace/__init__.py
vace/vace_ltx_inference.py
vace/vace_pipeline.py
vace/vace_preproccess.py
vace/vace_wan_inference.py
vace/annotators/__init__.py
vace/annotators/canvas.py
vace/annotators/common.py
vace/annotators/composition.py
vace/annotators/depth.py
vace/annotators/face.py
vace/annotators/flow.py
vace/annotators/frameref.py
vace/annotators/gdino.py
vace/annotators/gray.py
vace/annotators/inpainting.py
vace/annotators/layout.py
vace/annotators/mask.py
vace/annotators/maskaug.py
vace/annotators/outpainting.py
vace/annotators/pose.py
vace/annotators/prompt_extend.py
vace/annotators/ram.py
vace/annotators/salient.py
vace/annotators/sam.py
vace/annotators/sam2.py
vace/annotators/scribble.py
vace/annotators/subject.py
vace/annotators/utils.py
vace/annotators/dwpose/__init__.py
vace/annotators/dwpose/onnxdet.py
vace/annotators/dwpose/onnxpose.py
vace/annotators/dwpose/util.py
vace/annotators/dwpose/wholebody.py
vace/annotators/midas/__init__.py
vace/annotators/midas/api.py
vace/annotators/midas/base_model.py
vace/annotators/midas/blocks.py
vace/annotators/midas/dpt_depth.py
vace/annotators/midas/midas_net.py
vace/annotators/midas/midas_net_custom.py
vace/annotators/midas/transforms.py
vace/annotators/midas/utils.py
vace/annotators/midas/vit.py
vace/configs/__init__.py
vace/configs/common_preproccess.py
vace/configs/composition_preprocess.py
vace/configs/image_preproccess.py
vace/configs/prompt_preprocess.py
vace/configs/video_preproccess.py
vace/gradios/__init__.py
vace/gradios/vace_ltx_demo.py
vace/gradios/vace_preproccess_demo.py
vace/gradios/vace_wan_demo.py
vace/models/__init__.py
vace/models/ltx/__init__.py
vace/models/ltx/ltx_vace.py
vace/models/ltx/models/__init__.py
vace/models/ltx/models/transformers/__init__.py
vace/models/ltx/models/transformers/attention.py
vace/models/ltx/models/transformers/transformer3d.py
vace/models/ltx/pipelines/__init__.py
vace/models/ltx/pipelines/pipeline_ltx_video.py
vace/models/utils/__init__.py
vace-1.0.0.dist-info/METADATA
vace-1.0.0.dist-info/WHEEL
vace-1.0.0.dist-info/top_level.txt
vace-1.0.0.dist-info/RECORD
