Metadata-Version: 2.4
Name: vace
Version: 1.0.0
Summary: VACE: All-in-One Video Creation and Editing
Author-email: VACE Team <wan.ai@alibabacloud.com>
Project-URL: homepage, https://ali-vilab.github.io/VACE-Page/
Project-URL: documentation, https://ali-vilab.github.io/VACE-Page/
Project-URL: repository, https://github.com/ali-vilab/VACE
Project-URL: hfmodel, https://huggingface.co/collections/ali-vilab/vace-67eca186ff3e3564726aff38
Project-URL: msmodel, https://modelscope.cn/collections/VACE-8fa5fcfd386e43
Project-URL: paper, https://arxiv.org/abs/2503.07598
Requires-Python: <4.0,>=3.10
Requires-Dist: torch>=2.5.1
Requires-Dist: torchvision>=0.20.1
Requires-Dist: opencv-python>=4.9.0.80
Requires-Dist: diffusers>=0.31.0
Requires-Dist: transformers>=4.49.0
Requires-Dist: tokenizers>=0.20.3
Requires-Dist: accelerate>=1.1.1
Requires-Dist: gradio>=5.0.0
Requires-Dist: numpy<2,>=1.23.5
Requires-Dist: tqdm
Requires-Dist: imageio
Requires-Dist: easydict
Requires-Dist: ftfy
Requires-Dist: dashscope
Requires-Dist: imageio-ffmpeg
Requires-Dist: flash_attn
Requires-Dist: decord
Requires-Dist: einops
Requires-Dist: scikit-image
Requires-Dist: scikit-learn
Requires-Dist: pycocotools
Requires-Dist: timm
Requires-Dist: onnxruntime-gpu
Requires-Dist: BeautifulSoup4
